{
  "steps": [
    {
      "file": "docs/setup.md",
      "title": "快速开始",
      "shortTitle": "快速开始",
      "icon": "fa-rocket",
      "order": 1
    },
    {
      "file": "docs/deployment.md",
      "title": "部署指南",
      "shortTitle": "部署",
      "icon": "fa-cloud",
      "order": 2
    },
    {
      "file": "docs/authentication.md",
      "title": "认证配置",
      "shortTitle": "认证",
      "icon": "fa-lock",
      "order": 3
    },
    {
      "file": "docs/local-development.md",
      "title": "本地开发",
      "shortTitle": "本地开发",
      "icon": "fa-code",
      "order": 4
    },
    {
      "file": "docs/troubleshooting.md",
      "title": "常见问题",
      "shortTitle": "问题排查",
      "icon": "fa-question-circle",
      "order": 5
    },
    {
      "file": "docs/architecture.md",
      "title": "系统架构",
      "shortTitle": "架构流程",
      "icon": "fa-sitemap",
      "order": 6
    }
  ]
}

